
{
  "entities": {
    "User": {
      "$schema": "http://json-schema.org/draft-07/schema#",
      "title": "User",
      "type": "object",
      "description": "Represents a user of the CivisInsights AI application.",
      "properties": {
        "id": {
          "type": "string",
          "description": "Unique identifier for the user entity."
        },
        "googleId": {
          "type": "string",
          "description": "The unique Google ID associated with the user's Google account.",
          "format": "string"
        },
        "email": {
          "type": "string",
          "description": "The user's email address.",
          "format": "email"
        },
        "firstName": {
          "type": "string",
          "description": "The user's first name."
        },
        "lastName": {
          "type": "string",
          "description": "The user's last name."
        },
        "profilePicture": {
          "type": "string",
          "description": "URL of the user's profile picture.",
          "format": "uri"
        }
      },
      "required": [
        "id",
        "googleId",
        "email",
        "firstName",
        "lastName"
      ]
    }
  },
  "auth": {
    "providers": [
      "google.com"
    ]
  },
  "firestore": {
    "structure": [
      {
        "path": "/users/{userId}",
        "definition": {
          "entityName": "User",
          "schema": {
            "$ref": "#/backend/entities/User"
          },
          "description": "Stores user profile data. Access is restricted to the user identified by {userId}.",
          "params": [
            {
              "name": "userId",
              "description": "The unique identifier for the user."
            }
          ]
        }
      }
    ],
    "reasoning": "The Firestore structure is designed to securely manage user data for the CivisInsights AI application, focusing on simplicity, security, and scalability. User data is stored under the `/users/{userId}` path, ensuring path-based ownership for private data. This approach guarantees authorization independence because access control is directly tied to the user's ID in the path, eliminating the need for `get()` calls to parent documents. This structure supports required QAPs by isolating user data and providing a clear path-based authorization model."
  }
}
